simple_plotter/__init__.py
simple_plotter/cli.py
simple_plotter/core/__init__.py
simple_plotter/core/advanced_graph.py
simple_plotter/core/code_generator.py
simple_plotter/core/code_parser.py
simple_plotter/core/templates/template_constdef.txt
simple_plotter/core/templates/template_funcdef.txt
simple_plotter/core/templates/template_garden_graph_plot.txt
simple_plotter/core/templates/template_imports.txt
simple_plotter/core/templates/template_plotcall.txt
simple_plotter/core/templates/template_plotsetup.txt
simple_plotter/core/templates/template_setvardefs.txt
simple_plotter/core/templates/template_vardef.txt
simple_plotter/examples/ballistic.json
simple_plotter/examples/sine_waves.json
tests/__init__.py
tests/test_generator.py
tests/test_graph_advanced.py
tests/test_parser.py
simple_plotter-0.4.0.dist-info/LICENSE
simple_plotter-0.4.0.dist-info/METADATA
simple_plotter-0.4.0.dist-info/NOTICE
simple_plotter-0.4.0.dist-info/WHEEL
simple_plotter-0.4.0.dist-info/entry_points.txt
simple_plotter-0.4.0.dist-info/top_level.txt
simple_plotter-0.4.0.dist-info/RECORD
