Metadata-Version: 2.1
Name: simple-plotter
Version: 0.4.0
Summary: python code generator for plotting 2D line graphs
Home-page: https://simple-plotter.readthedocs.io/en/latest/
Author: Thies Hecker
Author-email: thies.hecker@gmx.de
License: MIT
Project-URL: Documentation, https://simple-plotter.readthedocs.io/
Project-URL: Source Code, https://gitlab.com/thecker/simple-plotter/
Keywords: plot plotting matplotlib numpy
Platform: UNKNOWN
Classifier: License :: OSI Approved :: MIT License
Requires-Python: >=3
Requires-Dist: numpy
Requires-Dist: setuptools-scm
Requires-Dist: jinja2
